[
  {
    "project": "Rijndael",
    "language": "PHP, JAVA",
    "description": "AES encrypt/decrypt, Android, iOS, PHP compatible. for java link: https://github.com/nzl-nadeem/rijndael",
    "link": "https://github.com/nzl-nadeem/rijndael"
  },
  {
    "project": "Mine Console",
    "language": "Android, Kotlin",
    "description": "An Android console view, which allows you to log text using static calls, to easily debug your application, whilst avoiding memory leaks.\n\nAn Android console view, which allows you to log text using static calls, to easily debug your application, whilst avoiding memory leaks.",
    "link": "https://github.com/nzl-nadeem/mineconsole"
  },
  {
    "project": "Geoip",
    "language": "PHP",
    "description": "This GeoIP and country lookup tool from UltraTools performs real-time lookups for an IP to return you the geographical location of the specific IP.",
    "link": "https://github.com/nzl-nadeem/geoip"
  },
  {
    "project": "php network toolkit",
    "language": "Shell, Python",
    "description": "Complete PHP Networking Toolkit",
    "link": "https://github.com/nzl-nadeem/php-network-toolkit"
  },
  {
    "project": "Medoo database framework",
    "language": "composer, PHP",
    "description": "The Lightweight PHP Database Framework to Accelerate Development",
    "link": "https://github.com/devsmine/medoo-database-framework"
  }
]